MANIFEST.in
README
setup.py
stdeb.cfg
data/certum_certificate.crt
data/e_szigno_test_tsa2.crt
data/fedict.crt
rfc3161/__init__.py
rfc3161/api.py
rfc3161/constants.py
rfc3161/types.py
rfc3161.egg-info/PKG-INFO
rfc3161.egg-info/SOURCES.txt
rfc3161.egg-info/dependency_links.txt
rfc3161.egg-info/requires.txt
rfc3161.egg-info/top_level.txt
spec/schema.asn88
tests/__init__.py
tests/api.py