Metadata-Version: 1.0
Name: rfc3161
Version: 1.0.4
Summary: Python implementation of the RFC3161 specification, using pyasn1
Home-page: https://dev.entrouvert.org/projects/python-rfc3161
Author: Benjamin Dauvergne
Author-email: bdauvergne@entrouvert.com
License: MIT
Platform: UNKNOWN
